02_rtl/COMMON/simple_dual_port_ram_single_clock.sv

// Quartus Prime Verilog Template
// Simple Dual Port RAM with separate read/write addresses and
// single read/write clock

module simple_dual_port_ram_single_clock
#(parameter DATA_WIDTH=8, parameter ADDR_WIDTH=6)
(
	input [(DATA_WIDTH-1):0] data,
	input [(ADDR_WIDTH-1):0] read_addr, write_addr,
	input we, clk,
	output reg [(DATA_WIDTH-1):0] q
);

	// Declare the RAM variable
	reg [DATA_WIDTH-1:0] ram[2**ADDR_WIDTH-1:0];

	always @ (posedge clk)
	begin
		// Write
		if (we)
			ram[write_addr] <= data;

		// Read (if read_addr == write_addr, return OLD data).	To return
		// NEW data, use = (blocking write) rather than <= (non-blocking write)
		// in the write assignment.	 NOTE: NEW data may require extra bypass
		// logic around the RAM.
		q <= ram[read_addr];
	end

endmodule

02_rtl/COMMON/fifo.sv
module fifo #(
    parameter SIZE_DATA  = 8,
    parameter SIZE_DEPTH = 16
)(
    input logic                     i_clk       ,
    input logic                     i_rst_n     ,
    input logic                     i_en_wr     ,
    input logic                     i_en_rd     ,
    input logic [SIZE_DATA-1:0]     i_data      ,
    output logic [SIZE_DATA-1:0]    o_data      ,
    output logic                    o_fifo_full ,
    output logic                    o_fifo_empty
);

// logic [SIZE_DATA-1:0] fifo_mem [0:SIZE_DEPTH-1];

localparam SIZE_ADDR = $clog2(SIZE_DEPTH);
logic [SIZE_ADDR:0] ptr_wr, ptr_rd;
logic [SIZE_ADDR:0] n_ptr_wr, n_ptr_rd;

assign o_fifo_empty = (ptr_wr == ptr_rd) ? 1'b1 : 1'b0;
assign o_fifo_full  = (~|(ptr_rd[SIZE_ADDR-1:0]^ptr_wr[SIZE_ADDR-1:0])) & (ptr_rd[SIZE_ADDR] ^ ptr_wr[SIZE_ADDR]);

logic w_update_wr, w_update_rd;
assign w_update_wr = i_en_wr & ~o_fifo_full;
assign n_ptr_wr = (w_update_wr) ? (ptr_wr + 1'b1) : ptr_wr;
assign w_update_rd = i_en_rd & ~o_fifo_empty;
assign n_ptr_rd = (w_update_rd) ? (ptr_rd + 1'b1) : ptr_rd;

always_ff @(posedge i_clk or negedge i_rst_n) begin
    if(~i_rst_n) 
        ptr_wr <= '0;
    else
        ptr_wr <= n_ptr_wr;
end 

always_ff @(posedge i_clk or negedge i_rst_n) begin
    if(~i_rst_n) 
        ptr_rd <= '0;
    else
        ptr_rd <= n_ptr_rd;
end 

logic [SIZE_DATA-1:0] w_odata;
simple_dual_port_ram_single_clock #(
    .DATA_WIDTH(SIZE_DATA), 
    .ADDR_WIDTH(SIZE_ADDR)
) dual_port_ram (
	.data       (i_data),
	.read_addr  (ptr_rd[SIZE_ADDR-1:0]),
    .write_addr (ptr_wr[SIZE_ADDR-1:0]),
	.we         (w_update_wr),
    .clk        (i_clk),
	.q          (w_odata)
);

always @(*) begin
    if(w_update_rd)
        o_data = w_odata;
    else
        o_data = '0;
end 

endmodule

02_test/FIFO/tb_fifo.sv
`timescale 1us / 1ps
module tb_fifo;

  parameter SIZE_DATA = 8;
  parameter SIZE_DEPTH = 16;
  localparam SIZE_ADDR = $clog2(SIZE_DEPTH);

  logic w_clk, w_rst_n;
  always #25 w_clk = ~w_clk; // clock generation FREQ = 50MHz

  logic w_fifo_full, w_fifo_empty;
  logic [SIZE_DATA-1:0] w_idata;
  logic [SIZE_DATA-1:0] w_odata;
  logic w_wr_en, w_rd_en;

  fifo #(
         .SIZE_DATA  (SIZE_DATA ),
         .SIZE_DEPTH (SIZE_DEPTH)
       ) uut (
         .i_clk          (w_clk),        // clock for CPU
         .i_rst_n        (w_rst_n),      // active low reset
         .i_en_wr        (w_wr_en),      // Enable write
         .i_en_rd        (w_rd_en),      // Enable read
         .i_data         (w_idata),      // data to be sent
         .o_data         (w_odata),      // data received
         .o_fifo_full    (w_fifo_full),  // FIFO full signal
         .o_fifo_empty   (w_fifo_empty)  // FIFO empty signal
       );
  initial
  begin
    $dumpfile("tb_fifo.vcd");
    $dumpvars(0, tb_fifo);
  end

  initial
  begin
    w_clk   = 1'b0;
    w_rst_n = 1'b0;
    w_wr_en = 1'b0;
    w_rd_en = 1'b0;
    w_idata = '0;
    #50 w_rst_n = 1'b1; // release reset
    $display("Reset at time %t", $time);
    #100;

    // Test case 1: Reset operation
    $display("Test case 1: Reset operation");
    w_wr_en = 1'b0; // Disable write
    w_rd_en = 1'b0; // Disable read
    @(posedge w_clk);
    #1;
    $display("Time=%t \t| i_data=%d \t| FIFO[%d]=%d \t|  ptr_rd=%d \t| ptr_wr=%d \t| o_full=%d \t| o_empty=%d \t|", $time - 1, w_idata, 0, w_odata, uut.ptr_rd[SIZE_ADDR-2:0], uut.ptr_wr[SIZE_ADDR-2:0], w_fifo_full, w_fifo_empty);
    // Check FIFO empty and full status
    $display("FIFO empty status: %d, FIFO full status: %d", w_fifo_empty, w_fifo_full);
    // Check FIFO pointers
    if (uut.ptr_rd == 0 && uut.ptr_wr == 0)
    begin
      $display("FIFO pointers are reset");
    end
    else
    begin
      $display("FIFO pointers are not reset");
    end

    #100;

    // Test write operation
    $display("Test case 2: Write operation");
    w_wr_en = 1'b1; // Enable write
    w_rd_en = 1'b0; // Disable read
    for (int i = 0; i < ((SIZE_DEPTH * 2) - 1); i++)
    begin
      w_idata = i;
      @(posedge w_clk);
      #1;
      $display("Time=%t \t| i_data=%d \t| FIFO[%d]=%d \t|  ptr_rd=%d \t| ptr_wr=%d \t| o_full=%d \t| o_empty=%d \t|", $time - 1, w_idata, i, w_odata, uut.ptr_rd[SIZE_ADDR-2:0], uut.ptr_wr[SIZE_ADDR-2:0], w_fifo_full, w_fifo_empty);
    end

    #100;

    // Test read operation
    $display("Test case 3: Read operation");
    w_wr_en = 1'b0; // Enable write
    w_rd_en = 1'b1; // Disable read
    for (int i = 0; i < ((SIZE_DEPTH * 2) - 1); i++)
    begin
      @(posedge w_clk);
      #1;
      $display("Time=%t \t| i_data=%d \t| FIFO[%d]=%d \t|  ptr_rd=%d \t| ptr_wr=%d \t| o_full=%d \t| o_empty=%d \t|", $time - 1, w_idata, i, w_odata, uut.ptr_rd[SIZE_ADDR-2:0], uut.ptr_wr[SIZE_ADDR-2:0], w_fifo_full, w_fifo_empty);
    end

    

    // Test case 4: FIFO read and write operation
    $display("Test case 4: FIFO read and write operation");
    @(posedge w_clk);
    w_wr_en = 1'b1; // Enable write
    w_rd_en = 1'b0; // Disable read
    w_idata = 8'h00; // Write data
    #1;
    $display("Time=%t \t| i_data=%d \t| FIFO[%d]=%d \t|  ptr_rd=%d \t| ptr_wr=%d \t| o_full=%d \t| o_empty=%d \t|", $time - 1, w_idata, 0, w_odata, uut.ptr_rd[SIZE_ADDR-2:0], uut.ptr_wr[SIZE_ADDR-2:0], w_fifo_full, w_fifo_empty);
    
    for(int i = 0; i < ((SIZE_DEPTH * 2) - 1); i++)
    begin
        @(posedge w_clk);
        w_wr_en = 1'b1; // Enable write
        w_rd_en = 1'b1; // Enable read
        w_idata = 8'h01 + i;
        #1;
        $display("Time=%t \t| i_data=%d \t| FIFO[%d]=%d \t|  ptr_rd=%d \t| ptr_wr=%d \t| o_full=%d \t| o_empty=%d \t|", $time - 1, w_idata, i, w_odata, uut.ptr_rd[SIZE_ADDR-2:0], uut.ptr_wr[SIZE_ADDR-2:0], w_fifo_full, w_fifo_empty);
    end

    #100 $finish; // finish simulation
  end

endmodule

02_test/FIFO/tb_fifo.vcd
$version Generated by VerilatedVcd $end
$timescale 1ps $end
 $scope module TOP $end
  $scope module tb_fifo $end
   $var wire 32 G SIZE_DATA [31:0] $end
   $var wire 32 H SIZE_DEPTH [31:0] $end
   $var wire 32 I SIZE_ADDR [31:0] $end
   $var wire 1 A w_clk $end
   $var wire 1 # w_rst_n $end
   $var wire 1 ; w_fifo_full $end
   $var wire 1 < w_fifo_empty $end
   $var wire 8 $ w_idata [7:0] $end
   $var wire 8 B w_odata [7:0] $end
   $var wire 1 % w_wr_en $end
   $var wire 1 & w_rd_en $end
   $scope module unnamedblk1 $end
    $var wire 32 ' i [31:0] $end
   $upscope $end
   $scope module unnamedblk2 $end
    $var wire 32 ( i [31:0] $end
   $upscope $end
   $scope module unnamedblk3 $end
    $var wire 32 ) i [31:0] $end
   $upscope $end
   $scope module uut $end
    $var wire 32 G SIZE_DATA [31:0] $end
    $var wire 32 H SIZE_DEPTH [31:0] $end
    $var wire 1 A i_clk $end
    $var wire 1 # i_rst_n $end
    $var wire 1 % i_en_wr $end
    $var wire 1 & i_en_rd $end
    $var wire 8 $ i_data [7:0] $end
    $var wire 8 B o_data [7:0] $end
    $var wire 1 ; o_fifo_full $end
    $var wire 1 < o_fifo_empty $end
    $var wire 32 I SIZE_ADDR [31:0] $end
    $var wire 5 = ptr_wr [4:0] $end
    $var wire 5 > ptr_rd [4:0] $end
    $var wire 5 C n_ptr_wr [4:0] $end
    $var wire 5 D n_ptr_rd [4:0] $end
    $var wire 1 E w_update_wr $end
    $var wire 1 F w_update_rd $end
    $var wire 8 * w_odata [7:0] $end
    $scope module dual_port_ram $end
     $var wire 32 G DATA_WIDTH [31:0] $end
     $var wire 32 I ADDR_WIDTH [31:0] $end
     $var wire 8 $ data [7:0] $end
     $var wire 4 ? read_addr [3:0] $end
     $var wire 4 @ write_addr [3:0] $end
     $var wire 1 E we $end
     $var wire 1 A clk $end
     $var wire 8 * q [7:0] $end
     $var wire 8 + ram[0] [7:0] $end
     $var wire 8 , ram[1] [7:0] $end
     $var wire 8 - ram[2] [7:0] $end
     $var wire 8 . ram[3] [7:0] $end
     $var wire 8 / ram[4] [7:0] $end
     $var wire 8 0 ram[5] [7:0] $end
     $var wire 8 1 ram[6] [7:0] $end
     $var wire 8 2 ram[7] [7:0] $end
     $var wire 8 3 ram[8] [7:0] $end
     $var wire 8 4 ram[9] [7:0] $end
     $var wire 8 5 ram[10] [7:0] $end
     $var wire 8 6 ram[11] [7:0] $end
     $var wire 8 7 ram[12] [7:0] $end
     $var wire 8 8 ram[13] [7:0] $end
     $var wire 8 9 ram[14] [7:0] $end
     $var wire 8 : ram[15] [7:0] $end
    $upscope $end
   $upscope $end
  $upscope $end
 $upscope $end
$enddefinitions $end


#0
0#
b00000000 $
0%
0&
b00000000000000000000000000000000 '
b00000000000000000000000000000000 (
b00000000000000000000000000000000 )
b00000000 *
b00000000 +
b00000000 ,
b00000000 -
b00000000 .
b00000000 /
b00000000 0
b00000000 1
b00000000 2
b00000000 3
b00000000 4
b00000000 5
b00000000 6
b00000000 7
b00000000 8
b00000000 9
b00000000 :
0;
1<
b00000 =
b00000 >
b0000 ?
b0000 @
0A
b00000000 B
b00000 C
b00000 D
0E
0F
b00000000000000000000000000001000 G
b00000000000000000000000000010000 H
b00000000000000000000000000000100 I
#25000000
1A
#50000000
1#
0A
#75000000
1A
#100000000
0A
#125000000
1A
#150000000
0A
#175000000
1A
#176000000
#200000000
0A
#225000000
1A
#250000000
0A
#275000000
1A
#276000000
1%
b00001 C
1E
#300000000
0A
#325000000
0<
b00001 =
b0001 @
1A
b00010 C
#326000000
b00000001 $
b00000000000000000000000000000001 '
#350000000
0A
#375000000
b00000001 ,
b00010 =
b0010 @
1A
b00011 C
#376000000
b00000010 $
b00000000000000000000000000000010 '
#400000000
0A
#425000000
b00000010 -
b00011 =
b0011 @
1A
b00100 C
#426000000
b00000011 $
b00000000000000000000000000000011 '
#450000000
0A
#475000000
b00000011 .
b00100 =
b0100 @
1A
b00101 C
#476000000
b00000100 $
b00000000000000000000000000000100 '
#500000000
0A
#525000000
b00000100 /
b00101 =
b0101 @
1A
b00110 C
#526000000
b00000101 $
b00000000000000000000000000000101 '
#550000000
0A
#575000000
b00000101 0
b00110 =
b0110 @
1A
b00111 C
#576000000
b00000110 $
b00000000000000000000000000000110 '
#600000000
0A
#625000000
b00000110 1
b00111 =
b0111 @
1A
b01000 C
#626000000
b00000111 $
b00000000000000000000000000000111 '
#650000000
0A
#675000000
b00000111 2
b01000 =
b1000 @
1A
b01001 C
#676000000
b00001000 $
b00000000000000000000000000001000 '
#700000000
0A
#725000000
b00001000 3
b01001 =
b1001 @
1A
b01010 C
#726000000
b00001001 $
b00000000000000000000000000001001 '
#750000000
0A
#775000000
b00001001 4
b01010 =
b1010 @
1A
b01011 C
#776000000
b00001010 $
b00000000000000000000000000001010 '
#800000000
0A
#825000000
b00001010 5
b01011 =
b1011 @
1A
b01100 C
#826000000
b00001011 $
b00000000000000000000000000001011 '
#850000000
0A
#875000000
b00001011 6
b01100 =
b1100 @
1A
b01101 C
#876000000
b00001100 $
b00000000000000000000000000001100 '
#900000000
0A
#925000000
b00001100 7
b01101 =
b1101 @
1A
b01110 C
#926000000
b00001101 $
b00000000000000000000000000001101 '
#950000000
0A
#975000000
b00001101 8
b01110 =
b1110 @
1A
b01111 C
#976000000
b00001110 $
b00000000000000000000000000001110 '
#1000000000
0A
#1025000000
b00001110 9
b01111 =
b1111 @
1A
b10000 C
#1026000000
b00001111 $
b00000000000000000000000000001111 '
#1050000000
0A
#1075000000
b00001111 :
1;
b10000 =
b0000 @
1A
0E
#1076000000
b00010000 $
b00000000000000000000000000010000 '
#1100000000
0A
#1125000000
1A
#1126000000
b00010001 $
b00000000000000000000000000010001 '
#1150000000
0A
#1175000000
1A
#1176000000
b00010010 $
b00000000000000000000000000010010 '
#1200000000
0A
#1225000000
1A
#1226000000
b00010011 $
b00000000000000000000000000010011 '
#1250000000
0A
#1275000000
1A
#1276000000
b00010100 $
b00000000000000000000000000010100 '
#1300000000
0A
#1325000000
1A
#1326000000
b00010101 $
b00000000000000000000000000010101 '
#1350000000
0A
#1375000000
1A
#1376000000
b00010110 $
b00000000000000000000000000010110 '
#1400000000
0A
#1425000000
1A
#1426000000
b00010111 $
b00000000000000000000000000010111 '
#1450000000
0A
#1475000000
1A
#1476000000
b00011000 $
b00000000000000000000000000011000 '
#1500000000
0A
#1525000000
1A
#1526000000
b00011001 $
b00000000000000000000000000011001 '
#1550000000
0A
#1575000000
1A
#1576000000
b00011010 $
b00000000000000000000000000011010 '
#1600000000
0A
#1625000000
1A
#1626000000
b00011011 $
b00000000000000000000000000011011 '
#1650000000
0A
#1675000000
1A
#1676000000
b00011100 $
b00000000000000000000000000011100 '
#1700000000
0A
#1725000000
1A
#1726000000
b00011101 $
b00000000000000000000000000011101 '
#1750000000
0A
#1775000000
1A
#1776000000
b00011110 $
b00000000000000000000000000011110 '
#1800000000
0A
#1825000000
1A
#1826000000
b00000000000000000000000000011111 '
#1850000000
0A
#1875000000
1A
#1900000000
0A
#1925000000
1A
#1926000000
0%
1&
b00001 D
1F
#1950000000
0A
#1975000000
0;
b00001 >
b0001 ?
1A
b00010 D
#1976000000
b00000000000000000000000000000001 (
#2000000000
0A
#2025000000
b00000001 *
b00010 >
b0010 ?
1A
b00000001 B
b00011 D
#2026000000
b00000000000000000000000000000010 (
#2050000000
0A
#2075000000
b00000010 *
b00011 >
b0011 ?
1A
b00000010 B
b00100 D
#2076000000
b00000000000000000000000000000011 (
#2100000000
0A
#2125000000
b00000011 *
b00100 >
b0100 ?
1A
b00000011 B
b00101 D
#2126000000
b00000000000000000000000000000100 (
#2150000000
0A
#2175000000
b00000100 *
b00101 >
b0101 ?
1A
b00000100 B
b00110 D
#2176000000
b00000000000000000000000000000101 (
#2200000000
0A
#2225000000
b00000101 *
b00110 >
b0110 ?
1A
b00000101 B
b00111 D
#2226000000
b00000000000000000000000000000110 (
#2250000000
0A
#2275000000
b00000110 *
b00111 >
b0111 ?
1A
b00000110 B
b01000 D
#2276000000
b00000000000000000000000000000111 (
#2300000000
0A
#2325000000
b00000111 *
b01000 >
b1000 ?
1A
b00000111 B
b01001 D
#2326000000
b00000000000000000000000000001000 (
#2350000000
0A
#2375000000
b00001000 *
b01001 >
b1001 ?
1A
b00001000 B
b01010 D
#2376000000
b00000000000000000000000000001001 (
#2400000000
0A
#2425000000
b00001001 *
b01010 >
b1010 ?
1A
b00001001 B
b01011 D
#2426000000
b00000000000000000000000000001010 (
#2450000000
0A
#2475000000
b00001010 *
b01011 >
b1011 ?
1A
b00001010 B
b01100 D
#2476000000
b00000000000000000000000000001011 (
#2500000000
0A
#2525000000
b00001011 *
b01100 >
b1100 ?
1A
b00001011 B
b01101 D
#2526000000
b00000000000000000000000000001100 (
#2550000000
0A
#2575000000
b00001100 *
b01101 >
b1101 ?
1A
b00001100 B
b01110 D
#2576000000
b00000000000000000000000000001101 (
#2600000000
0A
#2625000000
b00001101 *
b01110 >
b1110 ?
1A
b00001101 B
b01111 D
#2626000000
b00000000000000000000000000001110 (
#2650000000
0A
#2675000000
b00001110 *
b01111 >
b1111 ?
1A
b00001110 B
b10000 D
#2676000000
b00000000000000000000000000001111 (
#2700000000
0A
#2725000000
b00001111 *
1<
b10000 >
b0000 ?
1A
b00000000 B
0F
#2726000000
b00000000000000000000000000010000 (
#2750000000
0A
#2775000000
b00000000 *
1A
#2776000000
b00000000000000000000000000010001 (
#2800000000
0A
#2825000000
1A
#2826000000
b00000000000000000000000000010010 (
#2850000000
0A
#2875000000
1A
#2876000000
b00000000000000000000000000010011 (
#2900000000
0A
#2925000000
1A
#2926000000
b00000000000000000000000000010100 (
#2950000000
0A
#2975000000
1A
#2976000000
b00000000000000000000000000010101 (
#3000000000
0A
#3025000000
1A
#3026000000
b00000000000000000000000000010110 (
#3050000000
0A
#3075000000
1A
#3076000000
b00000000000000000000000000010111 (
#3100000000
0A
#3125000000
1A
#3126000000
b00000000000000000000000000011000 (
#3150000000
0A
#3175000000
1A
#3176000000
b00000000000000000000000000011001 (
#3200000000
0A
#3225000000
1A
#3226000000
b00000000000000000000000000011010 (
#3250000000
0A
#3275000000
1A
#3276000000
b00000000000000000000000000011011 (
#3300000000
0A
#3325000000
1A
#3326000000
b00000000000000000000000000011100 (
#3350000000
0A
#3375000000
1A
#3376000000
b00000000000000000000000000011101 (
#3400000000
0A
#3425000000
1A
#3426000000
b00000000000000000000000000011110 (
#3450000000
0A
#3475000000
1A
#3476000000
b00000000000000000000000000011111 (
#3500000000
0A
#3525000000
b00000000 $
1%
0&
0<
b10001 =
b0001 @
1A
b10010 C
1E
#3526000000
#3550000000
0A
#3575000000
b00000001 $
1&
b10010 =
b10001 >
b0001 ?
b0010 @
1A
b10011 C
b10010 D
1F
#3576000000
b00000000000000000000000000000001 )
#3600000000
0A
#3625000000
b00000010 $
b00000001 *
b10011 =
b10010 >
b0010 ?
b0011 @
1A
b00000001 B
b10100 C
b10011 D
#3626000000
b00000000000000000000000000000010 )
#3650000000
0A
#3675000000
b00000011 $
b00000010 *
b10100 =
b10011 >
b0011 ?
b0100 @
1A
b00000010 B
b10101 C
b10100 D
#3676000000
b00000000000000000000000000000011 )
#3700000000
0A
#3725000000
b00000100 $
b00000011 *
b10101 =
b10100 >
b0100 ?
b0101 @
1A
b00000011 B
b10110 C
b10101 D
#3726000000
b00000000000000000000000000000100 )
#3750000000
0A
#3775000000
b00000101 $
b00000100 *
b10110 =
b10101 >
b0101 ?
b0110 @
1A
b00000100 B
b10111 C
b10110 D
#3776000000
b00000000000000000000000000000101 )
#3800000000
0A
#3825000000
b00000110 $
b00000101 *
b10111 =
b10110 >
b0110 ?
b0111 @
1A
b00000101 B
b11000 C
b10111 D
#3826000000
b00000000000000000000000000000110 )
#3850000000
0A
#3875000000
b00000111 $
b00000110 *
b11000 =
b10111 >
b0111 ?
b1000 @
1A
b00000110 B
b11001 C
b11000 D
#3876000000
b00000000000000000000000000000111 )
#3900000000
0A
#3925000000
b00001000 $
b00000111 *
b11001 =
b11000 >
b1000 ?
b1001 @
1A
b00000111 B
b11010 C
b11001 D
#3926000000
b00000000000000000000000000001000 )
#3950000000
0A
#3975000000
b00001001 $
b00001000 *
b11010 =
b11001 >
b1001 ?
b1010 @
1A
b00001000 B
b11011 C
b11010 D
#3976000000
b00000000000000000000000000001001 )
#4000000000
0A
#4025000000
b00001010 $
b00001001 *
b11011 =
b11010 >
b1010 ?
b1011 @
1A
b00001001 B
b11100 C
b11011 D
#4026000000
b00000000000000000000000000001010 )
#4050000000
0A
#4075000000
b00001011 $
b00001010 *
b11100 =
b11011 >
b1011 ?
b1100 @
1A
b00001010 B
b11101 C
b11100 D
#4076000000
b00000000000000000000000000001011 )
#4100000000
0A
#4125000000
b00001100 $
b00001011 *
b11101 =
b11100 >
b1100 ?
b1101 @
1A
b00001011 B
b11110 C
b11101 D
#4126000000
b00000000000000000000000000001100 )
#4150000000
0A
#4175000000
b00001101 $
b00001100 *
b11110 =
b11101 >
b1101 ?
b1110 @
1A
b00001100 B
b11111 C
b11110 D
#4176000000
b00000000000000000000000000001101 )
#4200000000
0A
#4225000000
b00001110 $
b00001101 *
b11111 =
b11110 >
b1110 ?
b1111 @
1A
b00001101 B
b00000 C
b11111 D
#4226000000
b00000000000000000000000000001110 )
#4250000000
0A
#4275000000
b00001111 $
b00001110 *
b00000 =
b11111 >
b1111 ?
b0000 @
1A
b00001110 B
b00001 C
b00000 D
#4276000000
b00000000000000000000000000001111 )
#4300000000
0A
#4325000000
b00010000 $
b00001111 *
b00010000 +
b00001 =
b00000 >
b0000 ?
b0001 @
1A
b00001111 B
b00010 C
b00001 D
#4326000000
b00000000000000000000000000010000 )
#4350000000
0A
#4375000000
b00010001 $
b00010000 *
b00010001 ,
b00010 =
b00001 >
b0001 ?
b0010 @
1A
b00010000 B
b00011 C
b00010 D
#4376000000
b00000000000000000000000000010001 )
#4400000000
0A
#4425000000
b00010010 $
b00010001 *
b00010010 -
b00011 =
b00010 >
b0010 ?
b0011 @
1A
b00010001 B
b00100 C
b00011 D
#4426000000
b00000000000000000000000000010010 )
#4450000000
0A
#4475000000
b00010011 $
b00010010 *
b00010011 .
b00100 =
b00011 >
b0011 ?
b0100 @
1A
b00010010 B
b00101 C
b00100 D
#4476000000
b00000000000000000000000000010011 )
#4500000000
0A
#4525000000
b00010100 $
b00010011 *
b00010100 /
b00101 =
b00100 >
b0100 ?
b0101 @
1A
b00010011 B
b00110 C
b00101 D
#4526000000
b00000000000000000000000000010100 )
#4550000000
0A
#4575000000
b00010101 $
b00010100 *
b00010101 0
b00110 =
b00101 >
b0101 ?
b0110 @
1A
b00010100 B
b00111 C
b00110 D
#4576000000
b00000000000000000000000000010101 )
#4600000000
0A
#4625000000
b00010110 $
b00010101 *
b00010110 1
b00111 =
b00110 >
b0110 ?
b0111 @
1A
b00010101 B
b01000 C
b00111 D
#4626000000
b00000000000000000000000000010110 )
#4650000000
0A
#4675000000
b00010111 $
b00010110 *
b00010111 2
b01000 =
b00111 >
b0111 ?
b1000 @
1A
b00010110 B
b01001 C
b01000 D
#4676000000
b00000000000000000000000000010111 )
#4700000000
0A
#4725000000
b00011000 $
b00010111 *
b00011000 3
b01001 =
b01000 >
b1000 ?
b1001 @
1A
b00010111 B
b01010 C
b01001 D
#4726000000
b00000000000000000000000000011000 )
#4750000000
0A
#4775000000
b00011001 $
b00011000 *
b00011001 4
b01010 =
b01001 >
b1001 ?
b1010 @
1A
b00011000 B
b01011 C
b01010 D
#4776000000
b00000000000000000000000000011001 )
#4800000000
0A
#4825000000
b00011010 $
b00011001 *
b00011010 5
b01011 =
b01010 >
b1010 ?
b1011 @
1A
b00011001 B
b01100 C
b01011 D
#4826000000
b00000000000000000000000000011010 )
#4850000000
0A
#4875000000
b00011011 $
b00011010 *
b00011011 6
b01100 =
b01011 >
b1011 ?
b1100 @
1A
b00011010 B
b01101 C
b01100 D
#4876000000
b00000000000000000000000000011011 )
#4900000000
0A
#4925000000
b00011100 $
b00011011 *
b00011100 7
b01101 =
b01100 >
b1100 ?
b1101 @
1A
b00011011 B
b01110 C
b01101 D
#4926000000
b00000000000000000000000000011100 )
#4950000000
0A
#4975000000
b00011101 $
b00011100 *
b00011101 8
b01110 =
b01101 >
b1101 ?
b1110 @
1A
b00011100 B
b01111 C
b01110 D
#4976000000
b00000000000000000000000000011101 )
#5000000000
0A
#5025000000
b00011110 $
b00011101 *
b00011110 9
b01111 =
b01110 >
b1110 ?
b1111 @
1A
b00011101 B
b10000 C
b01111 D
#5026000000
b00000000000000000000000000011110 )
#5050000000
0A
#5075000000
b00011111 $
b00011110 *
b00011111 :
b10000 =
b01111 >
b1111 ?
b0000 @
1A
b00011110 B
b10001 C
b10000 D
#5076000000
b00000000000000000000000000011111 )
#5100000000
0A
#5125000000
b00011111 *
b00011111 +
b10001 =
b10000 >
b0000 ?
b0001 @
1A
b00011111 B
b10010 C
b10001 D
#5150000000
0A
#5175000000
b00011111 ,
b10010 =
b10001 >
b0001 ?
b0010 @
1A
b10011 C
b10010 D
