01_rtl/fifo.sv
module fifo #(
    parameter SIZE_DATA  = 8,
    parameter SIZE_DEPTH = 16
)(
    input  wire i_clk                        , // clock for CPU
    input  wire i_rst_n                      , // active low reset
    input  wire i_wr_en                      , // Enable write
    input  wire i_rd_en                      , // Enable read
    input  wire [SIZE_DATA-1:0] i_data       , // data to be sent
    output reg  [SIZE_DATA-1:0] o_data       , // data received
    output reg  o_fifo_full                  , // FIFO full signal
    output reg  o_fifo_empty                 //, // FIFO empty signal
    // output reg  o_error_overrun              // overrun error signal
);

localparam SIZE_ADDR = $clog2(SIZE_DEPTH);

reg [SIZE_ADDR:0] ptr_wr, n_ptr_wr, ptr_rd, n_ptr_rd; // write and read pointers
assign o_fifo_empty = (ptr_rd == ptr_wr) ? 1 : 0;
// assign o_full = (n_ptr_wr == ptr_rd) ? 1 : 0;
assign o_fifo_full = (~|(ptr_rd[SIZE_ADDR-1:0] ^ ptr_wr[SIZE_ADDR-1:0])) & (ptr_rd[SIZE_ADDR] ^ ptr_wr[SIZE_ADDR]);

wire w_update_wr;
wire w_update_rd;
assign w_update_wr = (i_wr_en & ~o_fifo_full); // write update signal
assign w_update_rd = (i_rd_en & ~o_fifo_empty); // read update signal

assign n_ptr_wr = (w_update_wr) ? (ptr_wr + 1) : ptr_wr; // next write pointer
assign n_ptr_rd = (w_update_rd) ? (ptr_rd + 1) : ptr_rd; // next read pointer
always_ff @( posedge i_clk or negedge i_rst_n ) begin : proc_point
    if(~i_rst_n) begin
        ptr_wr <= '0;
        ptr_rd <= '0;
    end else begin
        if (w_update_wr) begin
            ptr_wr <= n_ptr_wr;
        end
        if (w_update_rd) begin
            ptr_rd <= n_ptr_rd;
        end
    end
end

reg [SIZE_DATA-1:0] fifo_mem [0:SIZE_DEPTH-1]; // FIFO memory
always_ff @(posedge i_clk or negedge i_rst_n) begin : proc_fifo_write
    if(~i_rst_n) begin
        o_data <= '0;
    end else begin
        if(w_update_wr) begin
            fifo_mem[ptr_wr[SIZE_ADDR-1:0]] <= i_data; // write data to FIFO 
        end else begin
            fifo_mem[ptr_wr[SIZE_ADDR-1:0]] <= fifo_mem[ptr_wr[SIZE_ADDR-1:0]]; // keep data in FIFO    
        end
    end
end
always_ff @( posedge i_clk or negedge i_rst_n ) begin : proc_fifo_read
    if(~i_rst_n) begin
        o_data <= '0;
    end else begin
        if(w_update_rd) begin
            o_data <= fifo_mem[ptr_rd[SIZE_ADDR-1:0]]; // read data from FIFO
        end else begin
            o_data <= o_data; // keep data in FIFO    
        end
    end
end

endmodule

02_test/FIFO/tb_fifo.sv
`timescale 1us / 1ps
module tb_fifo;

  parameter SIZE_DATA = 8;
  parameter SIZE_DEPTH = 16;
  localparam SIZE_ADDR = $clog2(SIZE_DEPTH);

  logic w_clk, w_rst_n;
  always #25 w_clk = ~w_clk; // clock generation FREQ = 50MHz

  logic w_fifo_full, w_fifo_empty;
  logic [SIZE_DATA-1:0] w_idata;
  logic [SIZE_DATA-1:0] w_odata;
  logic w_wr_en, w_rd_en;

  fifo #(
         .SIZE_DATA  (SIZE_DATA ),
         .SIZE_DEPTH (SIZE_DEPTH)
       ) uut (
         .i_clk          (w_clk),        // clock for CPU
         .i_rst_n        (w_rst_n),      // active low reset
         .i_wr_en        (w_wr_en),      // Enable write
         .i_rd_en        (w_rd_en),      // Enable read
         .i_data         (w_idata),      // data to be sent
         .o_data         (w_odata),      // data received
         .o_fifo_full    (w_fifo_full),  // FIFO full signal
         .o_fifo_empty   (w_fifo_empty)  // FIFO empty signal
       );

  initial
  begin
    $dumpfile("tb_fifo.vcd");
    $dumpvars(0, tb_fifo);
  end

  initial
  begin
    w_clk   = 1'b0;
    w_rst_n = 1'b0;
    w_wr_en = 1'b0;
    w_rd_en = 1'b0;
    w_idata = '0;
    #50 w_rst_n = 1'b1; // release reset
    $display("Reset at time %t", $time);
    #100;

    // Test case 1: Reset operation
    $display("Test case 1: Reset operation");
    w_wr_en = 1'b0; // Disable write
    w_rd_en = 1'b0; // Disable read
    @(posedge w_clk);
    #1;
    $display("Time=%t \t| i_data=%d \t| FIFO[%d]=%d \t|  ptr_rd=%d \t| ptr_wr=%d \t| o_full=%d \t| o_empty=%d \t|", $time - 1, w_idata, 0, w_odata, uut.ptr_rd[SIZE_ADDR-2:0], uut.ptr_wr[SIZE_ADDR-2:0], w_fifo_full, w_fifo_empty);
    // Check FIFO empty and full status
    $display("FIFO empty status: %d, FIFO full status: %d", w_fifo_empty, w_fifo_full);
    // Check FIFO pointers
    if (uut.ptr_rd == 0 && uut.ptr_wr == 0)
    begin
      $display("FIFO pointers are reset");
    end
    else
    begin
      $display("FIFO pointers are not reset");
    end

    #100;

    // Test write operation
    $display("Test case 2: Write operation");
    w_wr_en = 1'b1; // Enable write
    w_rd_en = 1'b0; // Disable read
    for (int i = 0; i < ((SIZE_DEPTH * 2) - 1); i++)
    begin
      w_idata = i;
      @(posedge w_clk);
      #1;
      $display("Time=%t \t| i_data=%d \t| FIFO[%d]=%d \t|  ptr_rd=%d \t| ptr_wr=%d \t| o_full=%d \t| o_empty=%d \t|", $time - 1, w_idata, i, w_odata, uut.ptr_rd[SIZE_ADDR-2:0], uut.ptr_wr[SIZE_ADDR-2:0], w_fifo_full, w_fifo_empty);
    end

    #100;

    // Test read operation
    $display("Test case 3: Read operation");
    w_wr_en = 1'b0; // Enable write
    w_rd_en = 1'b1; // Disable read
    for (int i = 0; i < ((SIZE_DEPTH * 2) - 1); i++)
    begin
      @(posedge w_clk);
      #1;
      $display("Time=%t \t| i_data=%d \t| FIFO[%d]=%d \t|  ptr_rd=%d \t| ptr_wr=%d \t| o_full=%d \t| o_empty=%d \t|", $time - 1, w_idata, i, w_odata, uut.ptr_rd[SIZE_ADDR-2:0], uut.ptr_wr[SIZE_ADDR-2:0], w_fifo_full, w_fifo_empty);
    end

    

    // Test case 4: FIFO read and write operation
    $display("Test case 4: FIFO read and write operation");
    @(posedge w_clk);
    w_wr_en = 1'b1; // Enable write
    w_rd_en = 1'b0; // Disable read
    w_idata = 8'h00; // Write data
    #1;
    $display("Time=%t \t| i_data=%d \t| FIFO[%d]=%d \t|  ptr_rd=%d \t| ptr_wr=%d \t| o_full=%d \t| o_empty=%d \t|", $time - 1, w_idata, 0, w_odata, uut.ptr_rd[SIZE_ADDR-2:0], uut.ptr_wr[SIZE_ADDR-2:0], w_fifo_full, w_fifo_empty);
    
    for(int i = 0; i < ((SIZE_DEPTH * 2) - 1); i++)
    begin
        @(posedge w_clk);
        w_wr_en = 1'b1; // Enable write
        w_rd_en = 1'b1; // Enable read
        w_idata = 8'h01 + i;
        #1;
        $display("Time=%t \t| i_data=%d \t| FIFO[%d]=%d \t|  ptr_rd=%d \t| ptr_wr=%d \t| o_full=%d \t| o_empty=%d \t|", $time - 1, w_idata, i, w_odata, uut.ptr_rd[SIZE_ADDR-2:0], uut.ptr_wr[SIZE_ADDR-2:0], w_fifo_full, w_fifo_empty);
    end

    #100 $finish; // finish simulation
  end

endmodule

02_test/FIFO/tb_fifo.vcd
$version Generated by VerilatedVcd $end
$timescale 1ps $end
 $scope module TOP $end
  $scope module tb_fifo $end
   $var wire 32 D SIZE_DATA [31:0] $end
   $var wire 32 E SIZE_DEPTH [31:0] $end
   $var wire 32 F SIZE_ADDR [31:0] $end
   $var wire 1 ? w_clk $end
   $var wire 1 # w_rst_n $end
   $var wire 1 * w_fifo_full $end
   $var wire 1 + w_fifo_empty $end
   $var wire 8 $ w_idata [7:0] $end
   $var wire 8 , w_odata [7:0] $end
   $var wire 1 % w_wr_en $end
   $var wire 1 & w_rd_en $end
   $scope module unnamedblk1 $end
    $var wire 32 ' i [31:0] $end
   $upscope $end
   $scope module unnamedblk2 $end
    $var wire 32 ( i [31:0] $end
   $upscope $end
   $scope module unnamedblk3 $end
    $var wire 32 ) i [31:0] $end
   $upscope $end
   $scope module uut $end
    $var wire 32 D SIZE_DATA [31:0] $end
    $var wire 32 E SIZE_DEPTH [31:0] $end
    $var wire 1 ? i_clk $end
    $var wire 1 # i_rst_n $end
    $var wire 1 % i_wr_en $end
    $var wire 1 & i_rd_en $end
    $var wire 8 $ i_data [7:0] $end
    $var wire 8 , o_data [7:0] $end
    $var wire 1 * o_fifo_full $end
    $var wire 1 + o_fifo_empty $end
    $var wire 32 F SIZE_ADDR [31:0] $end
    $var wire 5 - ptr_wr [4:0] $end
    $var wire 5 @ n_ptr_wr [4:0] $end
    $var wire 5 . ptr_rd [4:0] $end
    $var wire 5 A n_ptr_rd [4:0] $end
    $var wire 1 B w_update_wr $end
    $var wire 1 C w_update_rd $end
    $var wire 8 / fifo_mem[0] [7:0] $end
    $var wire 8 0 fifo_mem[1] [7:0] $end
    $var wire 8 1 fifo_mem[2] [7:0] $end
    $var wire 8 2 fifo_mem[3] [7:0] $end
    $var wire 8 3 fifo_mem[4] [7:0] $end
    $var wire 8 4 fifo_mem[5] [7:0] $end
    $var wire 8 5 fifo_mem[6] [7:0] $end
    $var wire 8 6 fifo_mem[7] [7:0] $end
    $var wire 8 7 fifo_mem[8] [7:0] $end
    $var wire 8 8 fifo_mem[9] [7:0] $end
    $var wire 8 9 fifo_mem[10] [7:0] $end
    $var wire 8 : fifo_mem[11] [7:0] $end
    $var wire 8 ; fifo_mem[12] [7:0] $end
    $var wire 8 < fifo_mem[13] [7:0] $end
    $var wire 8 = fifo_mem[14] [7:0] $end
    $var wire 8 > fifo_mem[15] [7:0] $end
   $upscope $end
  $upscope $end
 $upscope $end
$enddefinitions $end


#0
0#
b00000000 $
0%
0&
b00000000000000000000000000000000 '
b00000000000000000000000000000000 (
b00000000000000000000000000000000 )
0*
1+
b00000000 ,
b00000 -
b00000 .
b00000000 /
b00000000 0
b00000000 1
b00000000 2
b00000000 3
b00000000 4
b00000000 5
b00000000 6
b00000000 7
b00000000 8
b00000000 9
b00000000 :
b00000000 ;
b00000000 <
b00000000 =
b00000000 >
0?
b00000 @
b00000 A
0B
0C
b00000000000000000000000000001000 D
b00000000000000000000000000010000 E
b00000000000000000000000000000100 F
#25000000
1?
#50000000
1#
0?
#75000000
1?
#100000000
0?
#125000000
1?
#150000000
0?
#175000000
1?
#176000000
#200000000
0?
#225000000
1?
#250000000
0?
#275000000
1?
#276000000
1%
b00001 @
1B
#300000000
0?
#325000000
0+
b00001 -
1?
b00010 @
#326000000
b00000001 $
b00000000000000000000000000000001 '
#350000000
0?
#375000000
b00010 -
b00000001 0
1?
b00011 @
#376000000
b00000010 $
b00000000000000000000000000000010 '
#400000000
0?
#425000000
b00011 -
b00000010 1
1?
b00100 @
#426000000
b00000011 $
b00000000000000000000000000000011 '
#450000000
0?
#475000000
b00100 -
b00000011 2
1?
b00101 @
#476000000
b00000100 $
b00000000000000000000000000000100 '
#500000000
0?
#525000000
b00101 -
b00000100 3
1?
b00110 @
#526000000
b00000101 $
b00000000000000000000000000000101 '
#550000000
0?
#575000000
b00110 -
b00000101 4
1?
b00111 @
#576000000
b00000110 $
b00000000000000000000000000000110 '
#600000000
0?
#625000000
b00111 -
b00000110 5
1?
b01000 @
#626000000
b00000111 $
b00000000000000000000000000000111 '
#650000000
0?
#675000000
b01000 -
b00000111 6
1?
b01001 @
#676000000
b00001000 $
b00000000000000000000000000001000 '
#700000000
0?
#725000000
b01001 -
b00001000 7
1?
b01010 @
#726000000
b00001001 $
b00000000000000000000000000001001 '
#750000000
0?
#775000000
b01010 -
b00001001 8
1?
b01011 @
#776000000
b00001010 $
b00000000000000000000000000001010 '
#800000000
0?
#825000000
b01011 -
b00001010 9
1?
b01100 @
#826000000
b00001011 $
b00000000000000000000000000001011 '
#850000000
0?
#875000000
b01100 -
b00001011 :
1?
b01101 @
#876000000
b00001100 $
b00000000000000000000000000001100 '
#900000000
0?
#925000000
b01101 -
b00001100 ;
1?
b01110 @
#926000000
b00001101 $
b00000000000000000000000000001101 '
#950000000
0?
#975000000
b01110 -
b00001101 <
1?
b01111 @
#976000000
b00001110 $
b00000000000000000000000000001110 '
#1000000000
0?
#1025000000
b01111 -
b00001110 =
1?
b10000 @
#1026000000
b00001111 $
b00000000000000000000000000001111 '
#1050000000
0?
#1075000000
1*
b10000 -
b00001111 >
1?
0B
#1076000000
b00010000 $
b00000000000000000000000000010000 '
#1100000000
0?
#1125000000
1?
#1126000000
b00010001 $
b00000000000000000000000000010001 '
#1150000000
0?
#1175000000
1?
#1176000000
b00010010 $
b00000000000000000000000000010010 '
#1200000000
0?
#1225000000
1?
#1226000000
b00010011 $
b00000000000000000000000000010011 '
#1250000000
0?
#1275000000
1?
#1276000000
b00010100 $
b00000000000000000000000000010100 '
#1300000000
0?
#1325000000
1?
#1326000000
b00010101 $
b00000000000000000000000000010101 '
#1350000000
0?
#1375000000
1?
#1376000000
b00010110 $
b00000000000000000000000000010110 '
#1400000000
0?
#1425000000
1?
#1426000000
b00010111 $
b00000000000000000000000000010111 '
#1450000000
0?
#1475000000
1?
#1476000000
b00011000 $
b00000000000000000000000000011000 '
#1500000000
0?
#1525000000
1?
#1526000000
b00011001 $
b00000000000000000000000000011001 '
#1550000000
0?
#1575000000
1?
#1576000000
b00011010 $
b00000000000000000000000000011010 '
#1600000000
0?
#1625000000
1?
#1626000000
b00011011 $
b00000000000000000000000000011011 '
#1650000000
0?
#1675000000
1?
#1676000000
b00011100 $
b00000000000000000000000000011100 '
#1700000000
0?
#1725000000
1?
#1726000000
b00011101 $
b00000000000000000000000000011101 '
#1750000000
0?
#1775000000
1?
#1776000000
b00011110 $
b00000000000000000000000000011110 '
#1800000000
0?
#1825000000
1?
#1826000000
b00000000000000000000000000011111 '
#1850000000
0?
#1875000000
1?
#1900000000
0?
#1925000000
1?
#1926000000
0%
1&
b00001 A
1C
#1950000000
0?
#1975000000
0*
b00001 .
1?
b00010 A
#1976000000
b00000000000000000000000000000001 (
#2000000000
0?
#2025000000
b00000001 ,
b00010 .
1?
b00011 A
#2026000000
b00000000000000000000000000000010 (
#2050000000
0?
#2075000000
b00000010 ,
b00011 .
1?
b00100 A
#2076000000
b00000000000000000000000000000011 (
#2100000000
0?
#2125000000
b00000011 ,
b00100 .
1?
b00101 A
#2126000000
b00000000000000000000000000000100 (
#2150000000
0?
#2175000000
b00000100 ,
b00101 .
1?
b00110 A
#2176000000
b00000000000000000000000000000101 (
#2200000000
0?
#2225000000
b00000101 ,
b00110 .
1?
b00111 A
#2226000000
b00000000000000000000000000000110 (
#2250000000
0?
#2275000000
b00000110 ,
b00111 .
1?
b01000 A
#2276000000
b00000000000000000000000000000111 (
#2300000000
0?
#2325000000
b00000111 ,
b01000 .
1?
b01001 A
#2326000000
b00000000000000000000000000001000 (
#2350000000
0?
#2375000000
b00001000 ,
b01001 .
1?
b01010 A
#2376000000
b00000000000000000000000000001001 (
#2400000000
0?
#2425000000
b00001001 ,
b01010 .
1?
b01011 A
#2426000000
b00000000000000000000000000001010 (
#2450000000
0?
#2475000000
b00001010 ,
b01011 .
1?
b01100 A
#2476000000
b00000000000000000000000000001011 (
#2500000000
0?
#2525000000
b00001011 ,
b01100 .
1?
b01101 A
#2526000000
b00000000000000000000000000001100 (
#2550000000
0?
#2575000000
b00001100 ,
b01101 .
1?
b01110 A
#2576000000
b00000000000000000000000000001101 (
#2600000000
0?
#2625000000
b00001101 ,
b01110 .
1?
b01111 A
#2626000000
b00000000000000000000000000001110 (
#2650000000
0?
#2675000000
b00001110 ,
b01111 .
1?
b10000 A
#2676000000
b00000000000000000000000000001111 (
#2700000000
0?
#2725000000
1+
b00001111 ,
b10000 .
1?
0C
#2726000000
b00000000000000000000000000010000 (
#2750000000
0?
#2775000000
1?
#2776000000
b00000000000000000000000000010001 (
#2800000000
0?
#2825000000
1?
#2826000000
b00000000000000000000000000010010 (
#2850000000
0?
#2875000000
1?
#2876000000
b00000000000000000000000000010011 (
#2900000000
0?
#2925000000
1?
#2926000000
b00000000000000000000000000010100 (
#2950000000
0?
#2975000000
1?
#2976000000
b00000000000000000000000000010101 (
#3000000000
0?
#3025000000
1?
#3026000000
b00000000000000000000000000010110 (
#3050000000
0?
#3075000000
1?
#3076000000
b00000000000000000000000000010111 (
#3100000000
0?
#3125000000
1?
#3126000000
b00000000000000000000000000011000 (
#3150000000
0?
#3175000000
1?
#3176000000
b00000000000000000000000000011001 (
#3200000000
0?
#3225000000
1?
#3226000000
b00000000000000000000000000011010 (
#3250000000
0?
#3275000000
1?
#3276000000
b00000000000000000000000000011011 (
#3300000000
0?
#3325000000
1?
#3326000000
b00000000000000000000000000011100 (
#3350000000
0?
#3375000000
1?
#3376000000
b00000000000000000000000000011101 (
#3400000000
0?
#3425000000
1?
#3426000000
b00000000000000000000000000011110 (
#3450000000
0?
#3475000000
1?
#3476000000
b00000000000000000000000000011111 (
#3500000000
0?
#3525000000
b00000000 $
1%
0&
0+
b10001 -
1?
b10010 @
1B
#3526000000
#3550000000
0?
#3575000000
b00000001 $
1&
b00000000 ,
b10010 -
b10001 .
1?
b10011 @
b10010 A
1C
#3576000000
b00000000000000000000000000000001 )
#3600000000
0?
#3625000000
b00000010 $
b00000001 ,
b10011 -
b10010 .
1?
b10100 @
b10011 A
#3626000000
b00000000000000000000000000000010 )
#3650000000
0?
#3675000000
b00000011 $
b00000010 ,
b10100 -
b10011 .
1?
b10101 @
b10100 A
#3676000000
b00000000000000000000000000000011 )
#3700000000
0?
#3725000000
b00000100 $
b00000011 ,
b10101 -
b10100 .
1?
b10110 @
b10101 A
#3726000000
b00000000000000000000000000000100 )
#3750000000
0?
#3775000000
b00000101 $
b00000100 ,
b10110 -
b10101 .
1?
b10111 @
b10110 A
#3776000000
b00000000000000000000000000000101 )
#3800000000
0?
#3825000000
b00000110 $
b00000101 ,
b10111 -
b10110 .
1?
b11000 @
b10111 A
#3826000000
b00000000000000000000000000000110 )
#3850000000
0?
#3875000000
b00000111 $
b00000110 ,
b11000 -
b10111 .
1?
b11001 @
b11000 A
#3876000000
b00000000000000000000000000000111 )
#3900000000
0?
#3925000000
b00001000 $
b00000111 ,
b11001 -
b11000 .
1?
b11010 @
b11001 A
#3926000000
b00000000000000000000000000001000 )
#3950000000
0?
#3975000000
b00001001 $
b00001000 ,
b11010 -
b11001 .
1?
b11011 @
b11010 A
#3976000000
b00000000000000000000000000001001 )
#4000000000
0?
#4025000000
b00001010 $
b00001001 ,
b11011 -
b11010 .
1?
b11100 @
b11011 A
#4026000000
b00000000000000000000000000001010 )
#4050000000
0?
#4075000000
b00001011 $
b00001010 ,
b11100 -
b11011 .
1?
b11101 @
b11100 A
#4076000000
b00000000000000000000000000001011 )
#4100000000
0?
#4125000000
b00001100 $
b00001011 ,
b11101 -
b11100 .
1?
b11110 @
b11101 A
#4126000000
b00000000000000000000000000001100 )
#4150000000
0?
#4175000000
b00001101 $
b00001100 ,
b11110 -
b11101 .
1?
b11111 @
b11110 A
#4176000000
b00000000000000000000000000001101 )
#4200000000
0?
#4225000000
b00001110 $
b00001101 ,
b11111 -
b11110 .
1?
b00000 @
b11111 A
#4226000000
b00000000000000000000000000001110 )
#4250000000
0?
#4275000000
b00001111 $
b00001110 ,
b00000 -
b11111 .
1?
b00001 @
b00000 A
#4276000000
b00000000000000000000000000001111 )
#4300000000
0?
#4325000000
b00010000 $
b00001111 ,
b00001 -
b00000 .
b00010000 /
1?
b00010 @
b00001 A
#4326000000
b00000000000000000000000000010000 )
#4350000000
0?
#4375000000
b00010001 $
b00010000 ,
b00010 -
b00001 .
b00010001 0
1?
b00011 @
b00010 A
#4376000000
b00000000000000000000000000010001 )
#4400000000
0?
#4425000000
b00010010 $
b00010001 ,
b00011 -
b00010 .
b00010010 1
1?
b00100 @
b00011 A
#4426000000
b00000000000000000000000000010010 )
#4450000000
0?
#4475000000
b00010011 $
b00010010 ,
b00100 -
b00011 .
b00010011 2
1?
b00101 @
b00100 A
#4476000000
b00000000000000000000000000010011 )
#4500000000
0?
#4525000000
b00010100 $
b00010011 ,
b00101 -
b00100 .
b00010100 3
1?
b00110 @
b00101 A
#4526000000
b00000000000000000000000000010100 )
#4550000000
0?
#4575000000
b00010101 $
b00010100 ,
b00110 -
b00101 .
b00010101 4
1?
b00111 @
b00110 A
#4576000000
b00000000000000000000000000010101 )
#4600000000
0?
#4625000000
b00010110 $
b00010101 ,
b00111 -
b00110 .
b00010110 5
1?
b01000 @
b00111 A
#4626000000
b00000000000000000000000000010110 )
#4650000000
0?
#4675000000
b00010111 $
b00010110 ,
b01000 -
b00111 .
b00010111 6
1?
b01001 @
b01000 A
#4676000000
b00000000000000000000000000010111 )
#4700000000
0?
#4725000000
b00011000 $
b00010111 ,
b01001 -
b01000 .
b00011000 7
1?
b01010 @
b01001 A
#4726000000
b00000000000000000000000000011000 )
#4750000000
0?
#4775000000
b00011001 $
b00011000 ,
b01010 -
b01001 .
b00011001 8
1?
b01011 @
b01010 A
#4776000000
b00000000000000000000000000011001 )
#4800000000
0?
#4825000000
b00011010 $
b00011001 ,
b01011 -
b01010 .
b00011010 9
1?
b01100 @
b01011 A
#4826000000
b00000000000000000000000000011010 )
#4850000000
0?
#4875000000
b00011011 $
b00011010 ,
b01100 -
b01011 .
b00011011 :
1?
b01101 @
b01100 A
#4876000000
b00000000000000000000000000011011 )
#4900000000
0?
#4925000000
b00011100 $
b00011011 ,
b01101 -
b01100 .
b00011100 ;
1?
b01110 @
b01101 A
#4926000000
b00000000000000000000000000011100 )
#4950000000
0?
#4975000000
b00011101 $
b00011100 ,
b01110 -
b01101 .
b00011101 <
1?
b01111 @
b01110 A
#4976000000
b00000000000000000000000000011101 )
#5000000000
0?
#5025000000
b00011110 $
b00011101 ,
b01111 -
b01110 .
b00011110 =
1?
b10000 @
b01111 A
#5026000000
b00000000000000000000000000011110 )
#5050000000
0?
#5075000000
b00011111 $
b00011110 ,
b10000 -
b01111 .
b00011111 >
1?
b10001 @
b10000 A
#5076000000
b00000000000000000000000000011111 )
#5100000000
0?
#5125000000
b00011111 ,
b10001 -
b10000 .
b00011111 /
1?
b10010 @
b10001 A
#5150000000
0?
#5175000000
b10010 -
b10001 .
b00011111 0
1?
b10011 @
b10010 A
